agent_protocol_client/__init__.py
agent_protocol_client/api/__init__.py
agent_protocol_client/api/agent_api.py
agent_protocol_client/api_client.py
agent_protocol_client/api_response.py
agent_protocol_client/configuration.py
agent_protocol_client/docs/AgentApi.md
agent_protocol_client/exceptions.py
agent_protocol_client/models/__init__.py
agent_protocol_client/models/artifact.py
agent_protocol_client/models/get_agent_task404_response.py
agent_protocol_client/models/pagination.py
agent_protocol_client/models/step.py
agent_protocol_client/models/step_all_of.py
agent_protocol_client/models/step_request_body.py
agent_protocol_client/models/step_result.py
agent_protocol_client/models/task.py
agent_protocol_client/models/task_all_of.py
agent_protocol_client/models/task_artifacts_list_response.py
agent_protocol_client/models/task_list_response.py
agent_protocol_client/models/task_request_body.py
agent_protocol_client/models/task_steps_list_response.py
agent_protocol_client/rest.py
agent_protocol_client/test/__init__.py
agent_protocol_client/test/test_agent_api.py
agent_protocol_client/test/test_artifact.py
agent_protocol_client/test/test_get_agent_task404_response.py
agent_protocol_client/test/test_pagination.py
agent_protocol_client/test/test_step.py
agent_protocol_client/test/test_step_request_body.py
agent_protocol_client/test/test_task.py
agent_protocol_client/test/test_task_artifacts_list_response.py
agent_protocol_client/test/test_task_list_response.py
agent_protocol_client/test/test_task_request_body.py
agent_protocol_client/test/test_task_steps_list_response.py
agent_protocol_client-1.1.0.dist-info/METADATA
agent_protocol_client-1.1.0.dist-info/WHEEL
agent_protocol_client-1.1.0.dist-info/RECORD
