Metadata-Version: 2.1
Name: agent-protocol-client
Version: 1.1.0
Summary: Agent Communication Protocol Client
Home-page: https://agentprotocol.ai/
License: MIT
Author: AI Engineers Foundation
Author-email: aiengineersfoundation@gmail.com
Requires-Python: >=3.7,<4.0
Classifier: License :: OSI Approved :: MIT License
Classifier: Programming Language :: Python :: 3
Classifier: Programming Language :: Python :: 3.7
Classifier: Programming Language :: Python :: 3.8
Classifier: Programming Language :: Python :: 3.9
Classifier: Programming Language :: Python :: 3.10
Classifier: Programming Language :: Python :: 3.11
Requires-Dist: aiohttp (>=3.8.4,<4.0.0)
Requires-Dist: pydantic (>=1.10.5,<2.0.0)
Requires-Dist: python-dateutil (>=2.8.2,<3.0.0)
Requires-Dist: urllib3 (>=1.25.3,<2.0.0)
Project-URL: Bug Tracker, https://github.com/AI-Engineers-Foundation/agent-protocol/issues
Project-URL: Repository, https://github.com/AI-Engineers-Foundation/agent-protocol/tree/main/packages/client/python
